mtmiifc/__init__.py
mtmiifc/callable_object.py
mtmiifc/pytorch_block.py
mtmiifc-0.1.1.dist-info/METADATA
mtmiifc-0.1.1.dist-info/WHEEL
mtmiifc-0.1.1.dist-info/top_level.txt
mtmiifc-0.1.1.dist-info/RECORD
