Metadata-Version: 2.4
Name: mtmiifc
Version: 0.1.1
Summary: Import callable objects from configuration dictionaries.
Author: Imutum
License: MIT
Keywords: config,dynamic-import,callable
Classifier: Development Status :: 3 - Alpha
Classifier: Programming Language :: Python :: 3.8
Classifier: Intended Audience :: Developers
Classifier: License :: OSI Approved :: MIT License
Classifier: Operating System :: MacOS
Classifier: Operating System :: POSIX :: Linux
Classifier: Operating System :: Microsoft :: Windows
Requires-Python: >=3.9
